buildbot_gitea/__init__.py
buildbot_gitea/auth.py
buildbot_gitea/reporter.py
buildbot_gitea/step_source.py
buildbot_gitea/webhook.py
buildbot_gitea-1.8.0.dist-info/LICENSE
buildbot_gitea-1.8.0.dist-info/METADATA
buildbot_gitea-1.8.0.dist-info/WHEEL
buildbot_gitea-1.8.0.dist-info/entry_points.txt
buildbot_gitea-1.8.0.dist-info/top_level.txt
buildbot_gitea-1.8.0.dist-info/RECORD
