Metadata-Version: 2.1
Name: buildbot-gitea
Version: 1.8.0
Summary: buildbot plugin for integration with Gitea.
Home-page: https://github.com/lab132/buildbot-gitea
Author: Marvin Pohl
Author-email: hello@lab132.com
Classifier: Development Status :: 5 - Production/Stable
Classifier: Environment :: Plugins
Classifier: Intended Audience :: Developers
Classifier: License :: OSI Approved :: MIT License
Classifier: Operating System :: Microsoft :: Windows
Classifier: Operating System :: MacOS
Classifier: Operating System :: POSIX :: Linux
Classifier: Topic :: Software Development :: Build Tools
License-File: LICENSE
Requires-Dist: buildbot (>=3.9.2)
